{
 "id": "krokorok",
 "name": "Krokorok",
 "dex": 552,
 "types": [
  "ground",
  "dark"
 ],
 "base_stats": {
  "hp": 60,
  "attack": 82,
  "defense": 45,
  "special_attack": 45,
  "special_defense": 45,
  "speed": 74
 },
 "abilities": [
  "intimidate",
  "moxie",
  "anger-point"
 ],
 "base_experience": 123,
 "growth_rate": "medium-slow",
 "catch_rate": 90,
 "gender_rate": 4,
 "learnset": {
  "level_up": [
   {
    "move": "leer",
    "level": 1
   },
   {
    "move": "rage",
    "level": 1
   },
   {
    "move": "bite",
    "level": 1
   },
   {
    "move": "sand-attack",
    "level": 1
   },
   {
    "move": "bite",
    "level": 4
   },
   {
    "move": "sand-attack",
    "level": 7
   },
   {
    "move": "torment",
    "level": 10
   },
   {
    "move": "sand-tomb",
    "level": 13
   },
   {
    "move": "assurance",
    "level": 16
   },
   {
    "move": "mud-slap",
    "level": 19
   },
   {
    "move": "embargo",
    "level": 22
   },
   {
    "move": "swagger",
    "level": 25
   },
   {
    "move": "crunch",
    "level": 28
   },
   {
    "move": "dig",
    "level": 32
   },
   {
    "move": "scary-face",
    "level": 36
   },
   {
    "move": "foul-play",
    "level": 40
   },
   {
    "move": "sandstorm",
    "level": 44
   },
   {
    "move": "earthquake",
    "level": 48
   },
   {
    "move": "thrash",
    "level": 52
   }
  ],
  "egg": [],
  "tutor": [
   "low-kick",
   "snore",
   "spite",
   "sleep-talk",
   "iron-tail",
   "uproar",
   "knock-off",
   "snatch",
   "dark-pulse",
   "aqua-tail",
   "earth-power",
   "stealth-rock",
   "foul-play"
  ],
  "machine": [
   "cut",
   "roar",
   "strength",
   "earthquake",
   "dig",
   "toxic",
   "double-team",
   "rest",
   "rock-slide",
   "substitute",
   "thief",
   "protect",
   "sludge-bomb",
   "sandstorm",
   "swagger",
   "attract",
   "return",
   "frustration",
   "hidden-power",
   "rock-smash",
   "torment",
   "facade",
   "taunt",
   "brick-break",
   "rock-tomb",
   "payback",
   "embargo",
   "fling",
   "shadow-claw",
   "stone-edge",
   "grass-knot",
   "hone-claws",
   "low-sweep",
   "round",
   "incinerate",
   "retaliate",
   "bulldoze",
   "snarl"
  ]
 }
}