{
 "id": "hurricane",
 "name": "Hurricane",
 "type": "flying",
 "category": "special",
 "power": 120,
 "accuracy": 70,
 "pp": 10,
 "priority": 0,
 "target": "selected-pokemon",
 "crit_stage": 0,
 "short_effect": "Has a chance to confuse the target.",
 "flags": [
  "distance",
  "mirror",
  "protect"
 ],
 "effect": {
  "kind": "damage-ailment",
  "ailment": "confusion",
  "ailment_chance": 30,
  "stat_changes": [],
  "stat_chance": 0,
  "flinch_chance": 0,
  "drain": 0,
  "healing": 0,
  "min_hits": null,
  "max_hits": null
 }
}